[
    {
        "name": "Staples",
        "img":"https://uploads-ssl.webflow.com/63e857eaeaf853471d5335ff/63e8c4e560afc2c49da53521_brand%20(3)-min.png",
        "deliveryTime": "Delivery within 24 hours"
    },
    {
        "name": "Grocery Outlet",
        "img":"https://uploads-ssl.webflow.com/63e857eaeaf853471d5335ff/63e8c4e5eaf8533b0958cefe_brand%20(5)-min.png",
        "deliveryTime":"Delivery within 24 hours"
    },
    {
        "name": "Sports Basement",
        "img":"https://uploads-ssl.webflow.com/63e857eaeaf853471d5335ff/63e8c4e4707380971125e685_brand%20(4)-min.png",
        "deliveryTime":"Delivery within 24 hours"
    },
    {
        "name": "Target",
        "img":"https://uploads-ssl.webflow.com/63e857eaeaf853471d5335ff/63e8c4e4c21faa5e03c209c5_brand%20(1)-min.png",
        "deliveryTime":"Delivery within 24 hours"
    },
    {
        "name": "Sprouts",
        "img":"https://uploads-ssl.webflow.com/63e857eaeaf853471d5335ff/63e8c4e58b497e41aa46b801_brand%20(8)-min.png",
        "deliveryTime":"Delivery within 24 hours"
    },
    {
        "name": "Mollie Stones",
        "img":"https://uploads-ssl.webflow.com/63e857eaeaf853471d5335ff/63e8c4e454ac2e9d497cb531_brand%20(6)-min.png",
        "deliveryTime":"Delivery within 24 hours"
    },
    {
        "name": "Container Store",
        "img":"https://uploads-ssl.webflow.com/63e857eaeaf853471d5335ff/63e8c4e460afc2193aa53511_brand%20(2)-min.png",
        "deliveryTime":"Delivery within 24 hours"
    },
    {
        "name": "Bevmo!",
        "img":"https://uploads-ssl.webflow.com/63e857eaeaf853471d5335ff/63e8c4e51eb4ad92a3e75673_brand%20(7)-min.png",
        "deliveryTime":"Delivery within 24 hours"
    }

]